manga_scraper/__init__.py
manga_scraper/__main__.py
manga_scraper-0.12.dist-info/METADATA
manga_scraper-0.12.dist-info/WHEEL
manga_scraper-0.12.dist-info/entry_points.txt
manga_scraper-0.12.dist-info/top_level.txt
manga_scraper-0.12.dist-info/RECORD
